pegen4cp/__init__.py
pegen4cp/__version__.py
pegen4cp/build.py
pegen4cp/generator.py
pegen4cp/main.py
pegen4cp/module_prefix.py
pegen4cp/module_suffix.py
pegen4cp-1.0.dist-info/LICENSE
pegen4cp-1.0.dist-info/METADATA
pegen4cp-1.0.dist-info/WHEEL
pegen4cp-1.0.dist-info/entry_points.txt
pegen4cp-1.0.dist-info/top_level.txt
pegen4cp-1.0.dist-info/RECORD
