Metadata-Version: 2.1
Name: pegen4cp
Version: 1.0
Summary: A pegen modification that generates a one-file complete parser
Author: nahco314
Author-email: nahco3_ta@yahoo.co.jp
License: MIT
Requires-Python: >=3.8
License-File: LICENSE
Requires-Dist: pegen
